pytest_ai1899/__init__.py
pytest_ai1899/plugin.py
pytest_ai1899-1.1.0.dist-info/LICENSE
pytest_ai1899-1.1.0.dist-info/METADATA
pytest_ai1899-1.1.0.dist-info/WHEEL
pytest_ai1899-1.1.0.dist-info/entry_points.txt
pytest_ai1899-1.1.0.dist-info/top_level.txt
pytest_ai1899-1.1.0.dist-info/RECORD
