Metadata-Version: 2.1
Name: pytest-ai1899
Version: 1.1.0
Summary: pytest plugin for connecting to ai1899 smart system stack
Home-page: https://github.com/Formartha/pytest-ai1899
Author: Mor Dabastany
License: MIT
Keywords: pyest-ai1899
Classifier: Development Status :: 5 - Production/Stable
Classifier: Framework :: Pytest
Classifier: Intended Audience :: Developers
Classifier: Operating System :: POSIX
Classifier: Operating System :: Microsoft :: Windows
Classifier: Operating System :: MacOS :: MacOS X
Classifier: Topic :: Software Development :: Quality Assurance
Classifier: Topic :: Software Development :: Testing
Classifier: Programming Language :: Python :: 3.11
License-File: LICENSE
Requires-Dist: requests
